PCA9685_servo_driver/__init__.py
PCA9685_servo_driver/pca9685.py
PCA9685_servo_driver/pca9685_constants.py
archive/issue.py
archive/play.py
archive/stepper_info_play.py
archive/tcp_receiver.py
archive/telemetrix-11-12.py
archive/telemetrix_10_17_10:14.py
archive/telemetrix_aio_socket.py
archive/udp2.py
arduino_json_evaluation/deserialize/__init__.py
arduino_json_evaluation/deserialize/deserialize_json.py
arduino_json_evaluation/deserialize/deserialize_msgpack.py
arduino_json_evaluation/deserialize/deserialize_no_json.py
arduino_json_evaluation/deserialize/deserialize_no_json_count.py
debugging_code/elektuur.py
debugging_code/restart.py
debugging_code/two_steppers.py
examples/2.py
examples/absolute4.py
examples/analog_input.py
examples/analog_input_scan_interval.py
examples/blink.py
examples/blink_play.py
examples/blink_time.py
examples/bme_id.py
examples/dac.py
examples/dht.py
examples/dht3.py
examples/dht_test.py
examples/digital_input.py
examples/digital_input_pullup.py
examples/fade.py
examples/fade2.py
examples/hard_reset_r4.py
examples/hc-sr04_distance2_sensor.py
examples/hc-sr04_distance_sensor.py
examples/i2c_adxl345_accelerometer.py
examples/i2c_adxl345_accelerometer2.py
examples/instantiate.py
examples/invoke.py
examples/loop_back.py
examples/onewire_ds18x20.py
examples/rotary_encoder.py
examples/servo.py
examples/servo2.py
examples/servo_and_pwm_test.py
examples/servo_multi.py
examples/simple_digital_input.py
examples/sonar_disable.py
examples/spi_adxl345_2.py
examples/spi_bme280.py
examples/spi_bme280_2.py
examples/spi_bme280_new.py
examples/spi_bme3.py
examples/spi_bme4.py
examples/spi_mpu9250.py
examples/stepper_absolute.py
examples/stepper_absolute2.py
examples/stepper_absolute3.py
examples/stepper_absolute_Uln2003-2.py
examples/stepper_absolute_Uln2003.py
examples/stepper_continuous.py
examples/stepper_relative.py
examples/stepper_relative2.py
examples/stepper_relative3.py
examples/stepper_run_speed_to_position.py
examples/stepper_set_and_get.py
telemetrix-1.45.dist-info/METADATA
telemetrix-1.45.dist-info/WHEEL
telemetrix-1.45.dist-info/top_level.txt
telemetrix-1.45.dist-info/RECORD
