Metadata-Version: 2.4
Name: telemetrix
Version: 1.45
Summary: Telemetrix Client
Author-email: Alan Yorinks <MisterYsLab@gmail.com>
License: AGPL-3.0-or-later
Project-URL: Homepage, https://github.com/MrYsLab/telemetrix
Project-URL: Issues, https://github.com/MrYsLab/telemetrix/issues
Keywords: telemetrix,Arduino,UNO,ESP8266,Python
Classifier: Development Status :: 5 - Production/Stable
Classifier: Environment :: Other Environment
Classifier: Intended Audience :: Developers
Classifier: Intended Audience :: Education
Classifier: Operating System :: OS Independent
Classifier: Topic :: Software Development :: Libraries :: Python Modules
Requires-Python: >=3.8
Requires-Dist: pyserial
Requires-Dist: bleak
